ament_cmake_target_dependencies/_dummy.cpython-310-x86_64-linux-gnu.so
ros_ament_cmake_target_dependencies-2.7.3.data/data/share/ament_cmake_target_dependencies/local_setup.bash
ros_ament_cmake_target_dependencies-2.7.3.data/data/share/ament_cmake_target_dependencies/local_setup.dsv
ros_ament_cmake_target_dependencies-2.7.3.data/data/share/ament_cmake_target_dependencies/local_setup.sh
ros_ament_cmake_target_dependencies-2.7.3.data/data/share/ament_cmake_target_dependencies/local_setup.zsh
ros_ament_cmake_target_dependencies-2.7.3.data/data/share/ament_cmake_target_dependencies/package.dsv
ros_ament_cmake_target_dependencies-2.7.3.data/data/share/ament_cmake_target_dependencies/package.xml
ros_ament_cmake_target_dependencies-2.7.3.data/data/share/ament_cmake_target_dependencies/cmake/ament_cmake_target_dependencies-extras.cmake
ros_ament_cmake_target_dependencies-2.7.3.data/data/share/ament_cmake_target_dependencies/cmake/ament_cmake_target_dependenciesConfig-version.cmake
ros_ament_cmake_target_dependencies-2.7.3.data/data/share/ament_cmake_target_dependencies/cmake/ament_cmake_target_dependenciesConfig.cmake
ros_ament_cmake_target_dependencies-2.7.3.data/data/share/ament_cmake_target_dependencies/cmake/ament_get_recursive_properties.cmake
ros_ament_cmake_target_dependencies-2.7.3.data/data/share/ament_cmake_target_dependencies/cmake/ament_target_dependencies.cmake
ros_ament_cmake_target_dependencies-2.7.3.data/data/share/ament_cmake_target_dependencies/environment/ament_prefix_path.dsv
ros_ament_cmake_target_dependencies-2.7.3.data/data/share/ament_cmake_target_dependencies/environment/ament_prefix_path.sh
ros_ament_cmake_target_dependencies-2.7.3.data/data/share/ament_cmake_target_dependencies/environment/path.dsv
ros_ament_cmake_target_dependencies-2.7.3.data/data/share/ament_cmake_target_dependencies/environment/path.sh
ros_ament_cmake_target_dependencies-2.7.3.dist-info/METADATA
ros_ament_cmake_target_dependencies-2.7.3.dist-info/WHEEL
ros_ament_cmake_target_dependencies-2.7.3.dist-info/top_level.txt
ros_ament_cmake_target_dependencies-2.7.3.dist-info/RECORD
