Metadata-Version: 2.4
Name: ros-ament-cmake-target-dependencies
Version: 2.7.3
Summary: Wheel for the ament_cmake_target_dependencies (ros-ament-cmake-target-dependencies) ROS 2 package.
Dynamic: description
Dynamic: description-content-type
Dynamic: summary
